qa4sm_reader/__init__.py
qa4sm_reader/colors.py
qa4sm_reader/comparing.py
qa4sm_reader/custom_intra_annual_windows_example.json
qa4sm_reader/custom_user_plot_generator.py
qa4sm_reader/exceptions.py
qa4sm_reader/globals.py
qa4sm_reader/handlers.py
qa4sm_reader/img.py
qa4sm_reader/intra_annual_temp_windows.py
qa4sm_reader/netcdf_transcription.py
qa4sm_reader/plot_all.py
qa4sm_reader/plotter.py
qa4sm_reader/plotting_methods.py
qa4sm_reader/utils.py
qa4sm_reader/static/images/logo/QA4SM_logo_long.png
qa4sm_reader/static/images/logo/qa4sm_logo_long.webp
qa4sm_reader-0.12.1.dist-info/licenses/AUTHORS.rst
qa4sm_reader-0.12.1.dist-info/licenses/LICENSE.txt
qa4sm_reader-0.12.1.dist-info/METADATA
qa4sm_reader-0.12.1.dist-info/WHEEL
qa4sm_reader-0.12.1.dist-info/top_level.txt
qa4sm_reader-0.12.1.dist-info/RECORD
