Metadata-Version: 2.4
Name: qa4sm_reader
Version: 0.12.1
Summary: Processes output of qa4sm.eodc.eu (NetCDF file), creating plots and providing the data in other formats.
Author-email: TU Wien <support@qa4sm.eu>
License: mit
Project-URL: Homepage, https://github.com/awst-austria/qa4sm-reader
Project-URL: Documentation, https://qa4sm-reader.readthedocs.io/en/latest/
Classifier: Development Status :: 4 - Beta
Classifier: Programming Language :: Python
Requires-Python: >=3.6
License-File: LICENSE.txt
License-File: AUTHORS.rst
Requires-Dist: importlib-metadata; python_version < "3.8"
Requires-Dist: xarray>=2024.0.0
Requires-Dist: pandas
Requires-Dist: numpy
Requires-Dist: netcdf4<1.7.3
Requires-Dist: h5netcdf
Requires-Dist: matplotlib
Requires-Dist: pyQt5
Requires-Dist: seaborn
Requires-Dist: cartopy>=0.23.0
Requires-Dist: colorcet
Requires-Dist: parse
Requires-Dist: scipy
Requires-Dist: pygeogrids
Requires-Dist: pytesmo
Provides-Extra: testing
Requires-Dist: pytest-cov; extra == "testing"
Requires-Dist: coverage; extra == "testing"
Requires-Dist: pytest; extra == "testing"
Provides-Extra: building
Requires-Dist: setuptools>=46.1.0; extra == "building"
Requires-Dist: setuptools_scm[toml]>=5; extra == "building"
Requires-Dist: wheel; extra == "building"
Requires-Dist: packaging; extra == "building"
Requires-Dist: build; extra == "building"
Requires-Dist: twine; extra == "building"
Provides-Extra: docs
Requires-Dist: sphinx<7,>=3.2.1; extra == "docs"
Requires-Dist: sphinx_rtd_theme; extra == "docs"
Requires-Dist: mock; extra == "docs"
Requires-Dist: pillow; extra == "docs"
Requires-Dist: recommonmark; extra == "docs"
Requires-Dist: readthedocs-sphinx-ext; extra == "docs"
Requires-Dist: myst_parser; extra == "docs"
Requires-Dist: nbsphinx; extra == "docs"
Dynamic: license-file
